fastecdsa/benchmark.py
fastecdsa/curvemath.cpython-310-darwin.so
fastecdsa/util.py
fastecdsa/__init__.py
fastecdsa/keys.py
fastecdsa/curve.py
fastecdsa/point.py
fastecdsa/ecdsa.py
fastecdsa/_ecdsa.cpython-310-darwin.so
fastecdsa/tests/test_point.py
fastecdsa/tests/test_keygen.py
fastecdsa/tests/test_nonce_generation.py
fastecdsa/tests/test_key_recovery.py
fastecdsa/tests/test_key_export_import.py
fastecdsa/tests/test_whycheproof_vectors.py
fastecdsa/tests/__init__.py
fastecdsa/tests/test_prehashed.py
fastecdsa/tests/test_brainpool_ecdh.py
fastecdsa/tests/test_rfc6979_ecdsa.py
fastecdsa/tests/test_whitespace_parsing.py
fastecdsa/tests/test_prime_field_curve_math.py
fastecdsa/tests/test_p256_ecdsa.py
fastecdsa/tests/encoding/test_sec1.py
fastecdsa/tests/encoding/__init__.py
fastecdsa/tests/encoding/test_der.py
fastecdsa/encoding/pem.py
fastecdsa/encoding/util.py
fastecdsa/encoding/__init__.py
fastecdsa/encoding/sec1.py
fastecdsa/encoding/der.py
fastecdsa/encoding/asn1.py
fastecdsa-2.3.1.dist-info/RECORD
fastecdsa-2.3.1.dist-info/LICENSE
fastecdsa-2.3.1.dist-info/WHEEL
fastecdsa-2.3.1.dist-info/top_level.txt
fastecdsa-2.3.1.dist-info/METADATA
