Metadata-Version: 2.1
Name: fastecdsa
Version: 2.3.1
Summary: Fast elliptic curve digital signatures
Author-email: Anton Kueltz <kueltz.anton@gmail.com>
License: This is free and unencumbered software released into the public domain.
Project-URL: repo, https://github.com/AntonKueltz/fastecdsa
Project-URL: docs, https://fastecdsa.readthedocs.io
Project-URL: pypi, https://pypi.org/project/fastecdsa/
Keywords: elliptic,curve,cryptography,ecdsa,ecc
Classifier: Development Status :: 4 - Beta
Classifier: Intended Audience :: Developers
Classifier: Topic :: Security :: Cryptography
Classifier: License :: CC0 1.0 Universal (CC0 1.0) Public Domain Dedication
Classifier: Programming Language :: Python :: 3.7
Classifier: Programming Language :: Python :: 3.8
Classifier: Programming Language :: Python :: 3.9
Classifier: Programming Language :: Python :: 3.10
Classifier: Programming Language :: Python :: 3.11
Classifier: Operating System :: MacOS :: MacOS X
Classifier: Operating System :: POSIX :: Linux
Requires-Python: >=3.7
License-File: LICENSE
